funROI/__init__.py
funROI/contrast.py
funROI/froi.py
funROI/parcels.py
funROI/settings.py
funROI/utils.py
funROI/analysis/__init__.py
funROI/analysis/effect.py
funROI/analysis/froi_gen.py
funROI/analysis/overlap.py
funROI/analysis/parcels_gen.py
funROI/analysis/spcorr.py
funROI/analysis/utils.py
funROI/datasets/__init__.py
funROI/datasets/hcp.py
funROI/first_level/__init__.py
funROI/first_level/nilearn.py
funROI/first_level/spm.py
funROI/first_level/utils.py
funroi-1.0.0.post1.dist-info/licenses/LICENSE
funroi-1.0.0.post1.dist-info/WHEEL
funroi-1.0.0.post1.dist-info/METADATA
funroi-1.0.0.post1.dist-info/RECORD
