Metadata-Version: 2.4
Name: funROI
Version: 1.0.0.post1
Summary: A Python package for functional ROI analyses of fMRI data
Keywords: fMRI,ROI,neuroimaging,data analysis
Author-email: Ruimin Gao <ruimin.gao@gatech.edu>, "Anna A. Ivanova" <a.ivanova@gatech.edu>
Classifier: Development Status :: 5 - Production/Stable
Classifier: Intended Audience :: Science/Research
Classifier: Topic :: Scientific/Engineering :: Medical Science Apps.
Classifier: License :: OSI Approved :: MIT License
Classifier: Programming Language :: Python :: 3.9
Classifier: Programming Language :: Python :: 3.10
Classifier: Programming Language :: Python :: 3.11
Classifier: Programming Language :: Python :: 3.12
Classifier: Programming Language :: Python :: 3.13
License-File: LICENSE
Requires-Dist: sphinx>=4.0
Requires-Dist: sphinx_rtd_theme
Requires-Dist: h5py>=3.0.0
Requires-Dist: nibabel>=5.2.0
Requires-Dist: numpy>=1.22.4
Requires-Dist: pandas>=2.2.0
Requires-Dist: scipy>=1.8.0
Requires-Dist: statsmodels
Requires-Dist: nilearn
